sugar/__init__.py
sugar/_action.py
sugar/_app.py
sugar/_constant.py
sugar/_eval.py
sugar/_formatter.py
sugar/_parser.py
sugar/_spec.py
sugar/_utils.py
sugar/exception.py
sugar/experimental/__init__.py
sugar/experimental/auto_pprint.py
sugar/experimental/lazy_import.py
sugar_cli-0.0.1.dev0.dist-info/LICENSE
sugar_cli-0.0.1.dev0.dist-info/WHEEL
sugar_cli-0.0.1.dev0.dist-info/METADATA
sugar_cli-0.0.1.dev0.dist-info/RECORD
