Metadata-Version: 2.3
Name: sugar-cli
Version: 0.0.1.dev0
Summary: Simple
Author-email: "Huang, Hong-Chang" <seer852741@gmail.com>
Requires-Python: >=3.12
Classifier: Development Status :: 3 - Alpha
Classifier: Intended Audience :: Developers
Classifier: License :: OSI Approved :: MIT License
Classifier: Programming Language :: Python :: 3.12
Classifier: Topic :: Software Development :: Libraries :: Python Modules
Requires-Dist: docstring-parser>=0.16
Project-URL: Homepage, https://github.com/Stanley5249/sugar
